seaplayer/__init__.py
seaplayer/__main__.py
seaplayer/assets/image-not-found.png
seaplayer/codecs/__init__.py
seaplayer/codecs/Any.py
seaplayer/codecs/AnySound.py
seaplayer/codecs/FLAC.py
seaplayer/codecs/MIDI.py
seaplayer/codecs/MP3.py
seaplayer/codecs/OGG.py
seaplayer/codecs/URLS.py
seaplayer/codecs/WAV.py
seaplayer/codeсbase.py
seaplayer/config.py
seaplayer/css/configurate.tcss
seaplayer/css/objects.tcss
seaplayer/css/seaplayer.tcss
seaplayer/css/unknown.tcss
seaplayer/exceptions.py
seaplayer/functions.py
seaplayer/langs/en-eng.properties
seaplayer/langs/ru-rus.properties
seaplayer/langs/uk-ukr.properties
seaplayer/languages.py
seaplayer/modules/__init__.py
seaplayer/modules/colorizer.py
seaplayer/objects/__init__.py
seaplayer/objects/Buttons.py
seaplayer/objects/Configurate.py
seaplayer/objects/DataOptions.py
seaplayer/objects/Image.py
seaplayer/objects/Input.py
seaplayer/objects/Labels.py
seaplayer/objects/Log.py
seaplayer/objects/Notification.py
seaplayer/objects/PlayList.py
seaplayer/objects/PopUp.py
seaplayer/objects/ProgressBar.py
seaplayer/objects/Radio.py
seaplayer/objects/Rheostat.py
seaplayer/plug/__init__.py
seaplayer/plug/__main__.py
seaplayer/plug/cli/__init__.py
seaplayer/plug/cli/cli.py
seaplayer/plug/cli/exceptions.py
seaplayer/plug/cli/functions.py
seaplayer/plug/cli/units.py
seaplayer/plug/pipw.py
seaplayer/plug/pluginbase.py
seaplayer/plug/pluginbase.pyi
seaplayer/plug/pluginloader.py
seaplayer/plug/pluginloader.pyi
seaplayer/screens/__init__.py
seaplayer/screens/Configurate.py
seaplayer/screens/Unknown.py
seaplayer/seaplayer.py
seaplayer/types/__init__.py
seaplayer/types/Cache.py
seaplayer/types/Convert.py
seaplayer/types/Environment.py
seaplayer/units.py
seaplayer-0.8.11.dist-info/entry_points.txt
seaplayer-0.8.11.dist-info/LICENSE
seaplayer-0.8.11.dist-info/METADATA
seaplayer-0.8.11.dist-info/WHEEL
seaplayer-0.8.11.dist-info/RECORD
