Metadata-Version: 2.1
Name: SeaPlayer
Version: 0.8.11
Summary: SeaPlayer is a player that works in the terminal.
Home-page: https://romanin-rf.github.io/SeaPlayer
License: MIT
Keywords: textual,tui,seaplayer,player,wav,mp3,ogg,flac,midi
Author: Romanin
Author-email: semina054@gmail.com
Requires-Python: >=3.8,<3.12
Classifier: Environment :: Console
Classifier: License :: OSI Approved :: MIT License
Classifier: Operating System :: MacOS
Classifier: Operating System :: Microsoft :: Windows :: Windows 10
Classifier: Operating System :: Microsoft :: Windows :: Windows 11
Classifier: Operating System :: POSIX :: Linux
Classifier: Programming Language :: Python :: 3
Classifier: Programming Language :: Python :: 3.8
Classifier: Programming Language :: Python :: 3.9
Classifier: Programming Language :: Python :: 3.10
Classifier: Programming Language :: Python :: 3.11
Provides-Extra: build
Provides-Extra: docs
Requires-Dist: aiofiles (>=23.1)
Requires-Dist: click (>=8)
Requires-Dist: mutagen (>=1.45)
Requires-Dist: pillow (>=9.5)
Requires-Dist: platformdirs (>=3.5)
Requires-Dist: playsoundsimple-py (==0.8.4)
Requires-Dist: poetry (>=1.5) ; extra == "build"
Requires-Dist: properties-py (==1.2.1)
Requires-Dist: pydantic (>=2.5)
Requires-Dist: pyinstaller (>=5.11) ; extra == "build"
Requires-Dist: rich (>=13) ; extra == "docs"
Requires-Dist: ripix (==2.5.0)
Requires-Dist: textual (>=0.43)
Requires-Dist: typing-extensions (>=4.6)
Requires-Dist: typing-inspect (>=0.9)
Requires-Dist: urlopen2 (==1.4.0)
Requires-Dist: validators (>=0.20)
Project-URL: Changelog, https://romanin-rf.github.io/SeaPlayer/changelog
Project-URL: Repository, https://github.com/romanin-rf/SeaPlayer
